scp_udg_client_rest/__init__.py
scp_udg_client_rest/api_client.py
scp_udg_client_rest/api_response.py
scp_udg_client_rest/configuration.py
scp_udg_client_rest/exceptions.py
scp_udg_client_rest/py.typed
scp_udg_client_rest/rest.py
scp_udg_client_rest/api/__init__.py
scp_udg_client_rest/api/urban_dataset_gateway_api.py
scp_udg_client_rest/models/__init__.py
scp_udg_client_rest/models/base_response.py
scp_udg_client_rest/models/basic_request.py
scp_udg_client_rest/models/deep_searching_request.py
scp_udg_client_rest/models/is_alive_response.py
scp_udg_client_rest/models/last_request.py
scp_udg_client_rest/models/login_request.py
scp_udg_client_rest/models/login_response.py
scp_udg_client_rest/models/push_request.py
scp_udg_client_rest/models/push_response.py
scp_udg_client_rest/models/scps_urbandataset_schema20.py
scp_udg_client_rest/models/scps_urbandataset_schema20_urban_dataset.py
scp_udg_client_rest/models/scps_urbandataset_schema20_urban_dataset_context.py
scp_udg_client_rest/models/scps_urbandataset_schema20_urban_dataset_context_coordinates.py
scp_udg_client_rest/models/scps_urbandataset_schema20_urban_dataset_context_producer.py
scp_udg_client_rest/models/scps_urbandataset_schema20_urban_dataset_specification.py
scp_udg_client_rest/models/scps_urbandataset_schema20_urban_dataset_specification_id.py
scp_udg_client_rest/models/scps_urbandataset_schema20_urban_dataset_specification_properties.py
scp_udg_client_rest/models/scps_urbandataset_schema20_urban_dataset_specification_properties_property_definition_inner.py
scp_udg_client_rest/models/scps_urbandataset_schema20_urban_dataset_specification_properties_property_definition_inner_sub_properties.py
scp_udg_client_rest/models/scps_urbandataset_schema20_urban_dataset_values.py
scp_udg_client_rest/models/scps_urbandataset_schema20_urban_dataset_values_line_inner.py
scp_udg_client_rest/models/scps_urbandataset_schema20_urban_dataset_values_line_inner_period.py
scp_udg_client_rest-1.0.0.dist-info/METADATA
scp_udg_client_rest-1.0.0.dist-info/WHEEL
scp_udg_client_rest-1.0.0.dist-info/top_level.txt
scp_udg_client_rest-1.0.0.dist-info/RECORD
